hexcolurs/__init__.py
hexcolurs/test.py
hexcolurs-1.4.dist-info/METADATA
hexcolurs-1.4.dist-info/WHEEL
hexcolurs-1.4.dist-info/top_level.txt
hexcolurs-1.4.dist-info/RECORD
