Metadata-Version: 2.1
Name: hexcolurs
Version: 1.4
Summary: Bring Colorful code in python
Author-email: admin.gmail@gmail.com
License: Eclipse Public License 2.0
